where/__init__.py
where/__main__.py
where/dirtree.py
where/utils.py
where_toy-0.0.9.dist-info/METADATA
where_toy-0.0.9.dist-info/WHEEL
where_toy-0.0.9.dist-info/licenses/LICENSE.txt
where_toy-0.0.9.dist-info/RECORD
