Metadata-Version: 2.1
Name: where-toy
Version: 0.0.9
Summary: Utility to locate python modules from the command line
Project-URL: homepage, https://github.com/furechan/where-toy
Author-email: furechan <furechan@xsmail.com>
License: MIT License
License-File: LICENSE.txt
Keywords: command-line,utility
Classifier: Development Status :: 2 - Pre-Alpha
Classifier: License :: OSI Approved :: MIT License
Classifier: Programming Language :: Python :: 3
Classifier: Topic :: Utilities
Requires-Python: >=3.9
Provides-Extra: dev
Requires-Dist: build; extra == 'dev'
Requires-Dist: invoke; extra == 'dev'
Requires-Dist: ipykernel; extra == 'dev'
Requires-Dist: nbmask; extra == 'dev'
Requires-Dist: pytest; extra == 'dev'
Requires-Dist: twine; extra == 'dev'
